{
    "last_updated": "2026-04-16T01:27:51.837749",
    "ab_available": true,
    "totals": {
        "views": 120,
        "scroll_25": 76,
        "scroll_50": 57,
        "scroll_75": 38,
        "scroll_100": 19,
        "clicks": 27,
        "leads": 1,
        "time_events": 107,
        "avg_session_duration_sec": 143
    },
    "ab_test": {
        "A": {
            "views": 51,
            "scroll_25": 0,
            "scroll_50": 0,
            "scroll_75": 0,
            "scroll_100": 0,
            "clicks": 13,
            "leads": 1,
            "time_events": 48
        },
        "B": {
            "views": 69,
            "scroll_25": 0,
            "scroll_50": 0,
            "scroll_75": 0,
            "scroll_100": 0,
            "clicks": 14,
            "leads": 0,
            "time_events": 59
        }
    },
    "channels": [
        {
            "source": "(not set)",
            "users": 38
        },
        {
            "source": "instagram / profile",
            "users": 32
        },
        {
            "source": "threads / post",
            "users": 25
        },
        {
            "source": "(direct) / (none)",
            "users": 13
        },
        {
            "source": "linkedin / post",
            "users": 9
        },
        {
            "source": "eo / post",
            "users": 3
        },
        {
            "source": "kakaotalk / community",
            "users": 3
        },
        {
            "source": "ig_text_feed_profile / post",
            "users": 1
        },
        {
            "source": "ig_text_post_permalink / post",
            "users": 1
        },
        {
            "source": "instagram / content",
            "users": 1
        },
        {
            "source": "linkedin / social",
            "users": 1
        },
        {
            "source": "tally.so / referral",
            "users": 1
        },
        {
            "source": "youtube / profile",
            "users": 1
        }
    ]
}